compress_pickle/__init__.py
compress_pickle/compress_pickle.py
compress_pickle/utils.py
compress_pickle/compressers/__init__.py
compress_pickle/compressers/base.py
compress_pickle/compressers/bz2.py
compress_pickle/compressers/gzip.py
compress_pickle/compressers/lz4.py
compress_pickle/compressers/lzma.py
compress_pickle/compressers/no_compression.py
compress_pickle/compressers/registry.py
compress_pickle/compressers/zipfile.py
compress_pickle/io/__init__.py
compress_pickle/io/base.py
compress_pickle/picklers/__init__.py
compress_pickle/picklers/base.py
compress_pickle/picklers/cloudpickle.py
compress_pickle/picklers/dill.py
compress_pickle/picklers/marshal.py
compress_pickle/picklers/optimized_pickle.py
compress_pickle/picklers/pickle.py
compress_pickle/picklers/registry.py
compress_pickle-2.1.0.dist-info/LICENSE
compress_pickle-2.1.0.dist-info/METADATA
compress_pickle-2.1.0.dist-info/WHEEL
compress_pickle-2.1.0.dist-info/top_level.txt
compress_pickle-2.1.0.dist-info/RECORD
