Metadata-Version: 2.1
Name: compress-pickle
Version: 2.1.0
Summary: Standard pickle, wrapped with standard compression libraries
Home-page: https://github.com/lucianopaz/compress_pickle
Author: Luciano Paz
Author-email: luciano.paz.neuro@gmail.com
License: UNKNOWN
Platform: UNKNOWN
Classifier: Programming Language :: Python :: 3
Classifier: License :: OSI Approved :: MIT License
Classifier: Operating System :: OS Independent
Requires-Python: >=3.6
Provides-Extra: lz4
Provides-Extra: dill
Provides-Extra: cloudpickle
Provides-Extra: full
License-File: LICENSE
